Deep4Cast/deep4cast/__init__.py
Deep4Cast/deep4cast/custom_layers.py
Deep4Cast/deep4cast/datasets.py
Deep4Cast/deep4cast/forecasters.py
Deep4Cast/deep4cast/metrics.py
Deep4Cast/deep4cast/models.py
Deep4Cast/deep4cast/transforms.py
azureml/contrib/__init__.py
azureml/contrib/automl/__init__.py
azureml/contrib/automl/dnn/__init__.py
azureml/contrib/automl/dnn/forecasting/__init__.py
azureml/contrib/automl/dnn/forecasting/constants.py
azureml/contrib/automl/dnn/forecasting/types.py
azureml/contrib/automl/dnn/forecasting/_distributed/__init__.py
azureml/contrib/automl/dnn/forecasting/_distributed/_data_for_inference.py
azureml/contrib/automl/dnn/forecasting/_distributed/_distributed_util.py
azureml/contrib/automl/dnn/forecasting/_distributed/_grain_summary.py
azureml/contrib/automl/dnn/forecasting/_distributed/_shard_summary.py
azureml/contrib/automl/dnn/forecasting/_distributed/_metrics/__init__.py
azureml/contrib/automl/dnn/forecasting/_distributed/_metrics/_explained_variance.py
azureml/contrib/automl/dnn/forecasting/_distributed/_metrics/_mae.py
azureml/contrib/automl/dnn/forecasting/_distributed/_metrics/_mape.py
azureml/contrib/automl/dnn/forecasting/_distributed/_metrics/_metric_util.py
azureml/contrib/automl/dnn/forecasting/_distributed/_metrics/_nmae.py
azureml/contrib/automl/dnn/forecasting/_distributed/_metrics/_nrmse.py
azureml/contrib/automl/dnn/forecasting/_distributed/_metrics/_nrmsle.py
azureml/contrib/automl/dnn/forecasting/_distributed/_metrics/_r2_score.py
azureml/contrib/automl/dnn/forecasting/_distributed/_metrics/_rmse.py
azureml/contrib/automl/dnn/forecasting/_distributed/_metrics/_rmsle.py
azureml/contrib/automl/dnn/forecasting/_distributed/_metrics/_supported_metrics.py
azureml/contrib/automl/dnn/forecasting/_distributed/_sharding/__init__.py
azureml/contrib/automl/dnn/forecasting/_distributed/_sharding/_download_shards.py
azureml/contrib/automl/dnn/forecasting/_distributed/_sharding/_equal_samples_sharding_strategy.py
azureml_contrib_automl_dnn_forecasting-1.61.0.post1.dist-info/licenses/LICENSE.txt
azureml_contrib_automl_dnn_forecasting-1.61.0.post1.dist-info/METADATA
azureml_contrib_automl_dnn_forecasting-1.61.0.post1.dist-info/WHEEL
azureml_contrib_automl_dnn_forecasting-1.61.0.post1.dist-info/top_level.txt
azureml_contrib_automl_dnn_forecasting-1.61.0.post1.dist-info/RECORD
