Metadata-Version: 2.4
Name: azureml-contrib-automl-dnn-forecasting
Version: 1.61.0.post1
Summary: Azure Automated Machine Learning DNN package for timeseries forecasting.
Home-page: https://docs.microsoft.com/python/api/overview/azure/ml/?view=azure-ml-py
Author: Microsoft Corp
License: Proprietary https://aka.ms/azureml-preview-sdk-license 
Classifier: Intended Audience :: Developers
Classifier: Intended Audience :: Science/Research
Classifier: Programming Language :: Python :: 3.8
Classifier: Programming Language :: Python :: 3.9
Classifier: Programming Language :: Python :: 3.10
Classifier: Programming Language :: Python :: 3.11
Classifier: Topic :: Scientific/Engineering :: Artificial Intelligence
Requires-Python: >=3.8,<4.0
License-File: LICENSE.txt
Requires-Dist: azureml-core~=1.61.0
Requires-Dist: azureml-automl-core~=1.61.0
Requires-Dist: azureml-automl-runtime~=1.61.0
Requires-Dist: azureml-train-automl-client~=1.61.0
Requires-Dist: azureml-train-automl-runtime~=1.61.0
Requires-Dist: azureml-dataset-runtime[pandas]~=1.61.0
Requires-Dist: GitPython>=3.1.37
Requires-Dist: overrides~=6.1.0
Requires-Dist: numpy<=1.21.6,>=1.16.0; python_version < "3.8"
Requires-Dist: numpy<=1.23.5,>=1.16.0; python_version >= "3.8"
Requires-Dist: pandas==1.5.3
Requires-Dist: tensorboard<2.13.0,>=2.4.1
Requires-Dist: torch==2.8.0
Requires-Dist: tqdm<=5.0.0,>=4.32.1
Requires-Dist: mlflow-skinny<=2.15.1
Dynamic: author
Dynamic: classifier
Dynamic: description
Dynamic: description-content-type
Dynamic: home-page
Dynamic: license
Dynamic: license-file
Dynamic: requires-dist
Dynamic: requires-python
Dynamic: summary
